easyssp_utils/__init__.py
easyssp_utils/client/__init__.py
easyssp_utils/client/api_client.py
easyssp_utils/client/api_response.py
easyssp_utils/client/configuration.py
easyssp_utils/client/exceptions.py
easyssp_utils/client/py.typed
easyssp_utils/client/rest.py
easyssp_utils/models/__init__.py
easyssp_utils/models/client_localized_message.py
easyssp_utils/models/error_message.py
easyssp_utils/models/localized_error_message.py
easyssp_utils/models/localized_message_key.py
easyssp_utils-1.0.0.dist-info/METADATA
easyssp_utils-1.0.0.dist-info/WHEEL
easyssp_utils-1.0.0.dist-info/licenses/LICENSE
easyssp_utils-1.0.0.dist-info/RECORD
