Metadata-Version: 2.4
Name: easyssp-utils
Version: 1.0.0
Summary: A collection of utilities to streamline interaction with the easySSP APIs.
Project-URL: Homepage, https://www.easy-ssp.com
Project-URL: Release Changelog, https://github.com/exxcellent/easyssp-python-clients-util/releases
Project-URL: Source, https://github.com/exxcellent/easyssp-python-clients-util
Author-email: easySSP Dev Team <easyssp-dev@exxcellent.de>
License: MIT
License-File: LICENSE
Keywords: client,easySSP,python,utils
Classifier: License :: OSI Approved :: MIT License
Classifier: Operating System :: OS Independent
Classifier: Programming Language :: Python :: 3.11
Requires-Python: >=3.11
Requires-Dist: easyssp-auth-client>=1.0.0
Requires-Dist: pydantic>=2.11.3
Requires-Dist: python-dateutil>=2.9.0.post0
Requires-Dist: types-python-dateutil>=2.9.0.20241206
Requires-Dist: urllib3>=2.4.0
